base/__init__.py
interface/__init__.py
yhd_acquisition-1.0.dist-info/METADATA
yhd_acquisition-1.0.dist-info/WHEEL
yhd_acquisition-1.0.dist-info/top_level.txt
yhd_acquisition-1.0.dist-info/RECORD
