Metadata-Version: 2.1
Name: yhd-acquisition
Version: 1.0
Summary: interface
Home-page: UNKNOWN
Author: 08479
License: MIT
Platform: UNKNOWN
Classifier: Programming Language :: Python :: 3
Classifier: License :: OSI Approved :: MIT License
Classifier: Operating System :: OS Independent
Requires-Python: >=3.6
